djld-1.0.2.dist-info/RECORD
djld-1.0.2.dist-info/metadata.json
djld-1.0.2.dist-info/WHEEL
djld-1.0.2.dist-info/DESCRIPTION.rst
djld-1.0.2.dist-info/top_level.txt
djld-1.0.2.dist-info/METADATA
tests/__init__.py
tests/test_djld.py
djld/__init__.py
djld/errors.py
djld/templatetags/djld.py
djld/templatetags/__init__.py
