Metadata-Version: 2.0
Name: djld
Version: 1.0.2
Summary: Structured data with Django
Home-page: https://github.com/lotrekagency/djld
Author: Lotrek
Author-email: dimmitutto@lotrek.it
License: MIT
Platform: UNKNOWN
Classifier: Environment :: Web Environment
Classifier: Framework :: Django
Classifier: Intended Audience :: Developers
Classifier: Programming Language :: Python
Classifier: Programming Language :: Python :: 3
